omniversion/__init__.py
omniversion/omniversion.py
omniversion/dashboard/__init__.py
omniversion/dashboard/terminal/__init__.py
omniversion/dashboard/terminal/__main__.py
omniversion/dashboard/website/__init__.py
omniversion/dashboard/website/__main__.py
omniversion/dashboard/website/template.html.j2
omniversion/dashboard/website/static/css/style.css
omniversion/dashboard/website/static/icons/cloud-download.svg
omniversion/dashboard/website/static/icons/files.svg
omniversion/dashboard/website/static/icons/lock-open.svg
omniversion/dashboard/website/static/icons/package.svg
omniversion/dashboard/website/static/icons/shield-lock.svg
omniversion/dashboard/website/static/icons/world-download.svg
omniversion/helpers/__init__.py
omniversion/helpers/helpers.py
omniversion/models/__init__.py
omniversion/models/data_source/__init__.py
omniversion/models/data_source/config.py
omniversion/models/data_source/data_sources.py
omniversion/models/data_source/file.py
omniversion/models/host/__init__.py
omniversion/models/host/host.py
omniversion/models/host/localhost.py
omniversion/models/package_manager/__init__.py
omniversion/models/package_manager/package_manager.py
omniversion/models/package_metadata/__init__.py
omniversion/models/package_metadata/advisory.py
omniversion/models/package_metadata/dependency_type.py
omniversion/models/package_metadata/installed_package.py
omniversion/models/package_metadata/package_metadata.py
omniversion/models/package_metadata/package_source.py
omniversion/models/package_metadata/list/__init__.py
omniversion/models/package_metadata/list/available_updates.py
omniversion/models/package_metadata/list/packages_metadata_list.py
omniversion/models/package_metadata/list/versions_match.py
omniversion/models/package_metadata/list/vulnerabilities.py
omniversion/pretty_print/__init__.py
omniversion/pretty_print/data_source.py
omniversion/pretty_print/helpers.py
omniversion/pretty_print/host.py
omniversion/pretty_print/omniversion.py
omniversion-0.47.0.dist-info/METADATA
omniversion-0.47.0.dist-info/WHEEL
omniversion-0.47.0.dist-info/top_level.txt
omniversion-0.47.0.dist-info/RECORD
