Metadata-Version: 2.1
Name: omniversion
Version: 0.47.0
Summary: Omniversion Python integration
Home-page: https://github.com/omniversion/omniversion
Author: Layer9 GmbH
Author-email: hello@layer9.berlin
License: AGPL-v3.0-only
Requires-Python: >=3.8
Requires-Dist: colorama
Requires-Dist: dacite
Requires-Dist: Jinja2
Requires-Dist: PyYAML
